flyingsnake/__init__.py
flyingsnake/__main__.py
flyingsnake/default_colors.py
flyingsnake/example_colors.json
flyingsnake/get_colors.py
flyingsnake-3.1.2.dist-info/METADATA
flyingsnake-3.1.2.dist-info/WHEEL
flyingsnake-3.1.2.dist-info/entry_points.txt
flyingsnake-3.1.2.dist-info/licenses/LICENSE.txt
flyingsnake-3.1.2.dist-info/RECORD
