Metadata-Version: 2.3
Name: flyingsnake
Version: 3.1.2
Summary: CLI Terraria world map renderer
Project-URL: Repository, https://forge.steffo.eu/steffo/flyingsnake/
Author-email: Stefano Pigozzi <me@steffo.eu>
Maintainer-email: Stefano Pigozzi <me@steffo.eu>
License-Expression: EUPL-1.2
License-File: LICENSE.txt
Keywords: game,lihzahrd,parser,terraria
Classifier: Development Status :: 4 - Beta
Classifier: Operating System :: OS Independent
Classifier: Programming Language :: Python :: 3.6
Requires-Python: >=3.6.2
Requires-Dist: click>=8.0.4
Requires-Dist: lihzahrd>=3.1.1
Requires-Dist: pillow>=8.4.0
